tickstore/__init__.py
tickstore/client.py
tickstore/db/__init__.py
tickstore/db/base_objects.py
tickstore/db/delta_buffer.py
tickstore/db/test.py
tickstore/db/types.py
tickstore/db/varint.py
tickstore/query/__init__.py
tickstore/query/query.py
tickstore/query/query_group.py
tickstore/query/query_settings.py
tickstore/query/sampler.py
tickstore/writers/__init__.py
tickstore/writers/tick_writer.py
tickstore_python_client-1.0.5.dist-info/METADATA
tickstore_python_client-1.0.5.dist-info/WHEEL
tickstore_python_client-1.0.5.dist-info/top_level.txt
tickstore_python_client-1.0.5.dist-info/RECORD
