Metadata-Version: 2.1
Name: tickstore-python-client
Version: 1.0.5
Summary: client to communicate with tickstore
Home-page: https://gitlab.com/alphaticks/tickstore-python-client
Author: Alphaticks
License: copyright
Requires-Dist: protobuf (==4.21.12)
Requires-Dist: tickstore-grpc (==1.0.3)
